repr_net/__init__.py
repr_net/base.py
repr_net/bibtex.py
repr_net/indexing.py
repr_net/visualization.py
repr_net-0.0.1.dist-info/METADATA
repr_net-0.0.1.dist-info/WHEEL
repr_net-0.0.1.dist-info/top_level.txt
repr_net-0.0.1.dist-info/RECORD
