Metadata-Version: 2.2
Name: repr_net
Version: 0.0.1
Summary: Build and visualize representation networks with Python
Author: Zijian Zhang
Project-URL: Homepage, https://github.com/aspuru-guzik-group/ReprNet
Project-URL: Issues, https://github.com/aspuru-guzik-group/ReprNet/issues
Requires-Python: >=3.8
Requires-Dist: bibtexparser~=1.4.3
Requires-Dist: networkx~=3.4.2
